time/__init__.py
time/time_utils.py
autumn_rain_py_sdk-0.0.1.dist-info/LICENSE
autumn_rain_py_sdk-0.0.1.dist-info/METADATA
autumn_rain_py_sdk-0.0.1.dist-info/WHEEL
autumn_rain_py_sdk-0.0.1.dist-info/top_level.txt
autumn_rain_py_sdk-0.0.1.dist-info/RECORD
