Metadata-Version: 2.1
Name: autumn-rain-py-sdk
Version: 0.0.1
Summary: python相关的通用工具集合
Home-page: https://gitee.com/yanghao170/autumn_rain_py_sdk.git
Author: qiwa
Author-email: yanghao170@aliyun.com
License: UNKNOWN
Platform: UNKNOWN
Classifier: Programming Language :: Python :: 3
Classifier: License :: OSI Approved :: MIT License
Classifier: Operating System :: OS Independent
Requires-Python: >=3.8
License-File: LICENSE
